[{"count":0.3,"cover":"https://assets.ppy.sh/beatmaps/1238516/covers/list.jpg?1622195695","id":1238516,"artist":"Noah","title":"Adrastea","ranked_date":"2020-09-06T16:04:19+00:00"},{"count":0.3,"cover":"https://assets.ppy.sh/beatmaps/1282013/covers/list.jpg?1622199965","id":1282013,"artist":"Noah","title":"Gentiana","ranked_date":"2020-11-08T21:02:13+00:00"},{"count":0.3,"cover":"https://assets.ppy.sh/beatmaps/1315184/covers/list.jpg?1609581649","id":1315184,"artist":"Noah","title":"World's end","ranked_date":null},{"count":0.3,"cover":"https://assets.ppy.sh/beatmaps/1426912/covers/list.jpg?1622208957","id":1426912,"artist":"Noah","title":"Reflection","ranked_date":"2021-05-12T07:01:53+00:00"},{"count":0.3,"cover":"https://assets.ppy.sh/beatmaps/1428289/covers/list.jpg?1626095397","id":1428289,"artist":"Noah","title":"Acacia","ranked_date":"2021-07-24T13:40:59+00:00"}]