[{"count":1.5,"cover":"https://assets.ppy.sh/beatmaps/1471183/covers/list.jpg?1627455623","id":1471183,"artist":"Kisaragi Rumii x DS","title":"Remote Control","ranked_date":null},{"count":1,"cover":"https://assets.ppy.sh/beatmaps/1222326/covers/list.jpg?1600176620","id":1222326,"artist":"Yuaru","title":"Asu no Yozora Shoukaihan","ranked_date":null},{"count":1,"cover":"https://assets.ppy.sh/beatmaps/1350472/covers/list.jpg?1622205482","id":1350472,"artist":"Nakanoke no Itsutsugo","title":"Gotoubun no Katachi (TV Size)","ranked_date":"2021-05-27T18:05:22+00:00"},{"count":1,"cover":"https://assets.ppy.sh/beatmaps/1371144/covers/list.jpg?1641632452","id":1371144,"artist":"Kisaragi Rumii, LAAM","title":"World's End Dancehall -World's End Dancehall Cantonese ver.-","ranked_date":null},{"count":1,"cover":"https://assets.ppy.sh/beatmaps/1407275/covers/list.jpg?1620718224","id":1407275,"artist":"Uchida Maaya","title":"youthful beautiful","ranked_date":null},{"count":0.5,"cover":"https://assets.ppy.sh/beatmaps/1522733/covers/list.jpg?1634310597","id":1522733,"artist":"wotoha","title":"Digital Life Hacker","ranked_date":"2021-10-23T08:24:21+00:00"},{"count":0.5,"cover":"https://assets.ppy.sh/beatmaps/1649954/covers/list.jpg?1644173653","id":1649954,"artist":"Mameyudoufu","title":"Wave feat. Aitsuki Nakuru","ranked_date":null}]