[{"count":1,"cover":"https://assets.ppy.sh/beatmaps/1138639/covers/list.jpg?1622185583","id":1138639,"artist":"Kakka","title":"Ningyou wa Tasogare ni Yume o Miru ka","ranked_date":"2020-12-13T13:44:32+00:00"},{"count":1,"cover":"https://assets.ppy.sh/beatmaps/1339896/covers/list.jpg?1640841838","id":1339896,"artist":"TEARS OF TRAGEDY","title":"Spring Memory","ranked_date":"2022-01-08T22:22:13+00:00"},{"count":1,"cover":"https://assets.ppy.sh/beatmaps/1454027/covers/list.jpg?1626291628","id":1454027,"artist":"Various Artists","title":"Hashire Uma Musume","ranked_date":"2021-07-22T00:02:08+00:00"}]