[{"count":1.4,"cover":"https://assets.ppy.sh/beatmaps/1482069/covers/list.jpg?1642190500","id":1482069,"artist":"xi","title":"Ascension to Heaven","ranked_date":"2022-01-17T13:02:22+00:00"},{"count":1,"cover":"https://assets.ppy.sh/beatmaps/1156499/covers/list.jpg?1593365437","id":1156499,"artist":"HoneyWorks","title":"Akatsuki Zukuyo","ranked_date":null},{"count":1,"cover":"https://assets.ppy.sh/beatmaps/1253816/covers/list.jpg?1606899661","id":1253816,"artist":"MY FIRST STORY feat. chelly (EGOIST)","title":"1,000,000 TIMES","ranked_date":null},{"count":1,"cover":"https://assets.ppy.sh/beatmaps/1285167/covers/list.jpg?1625685769","id":1285167,"artist":"Alvaro Soler","title":"Sofia (Sped Up Ver.)","ranked_date":"2021-07-16T22:24:10+00:00"},{"count":1,"cover":"https://assets.ppy.sh/beatmaps/1374425/covers/list.jpg?1627419181","id":1374425,"artist":"KISIDA KYODAN & THE AKEBOSI ROCKETS","title":"night birds (Cut Ver.)","ranked_date":"2021-08-04T01:45:12+00:00"},{"count":1,"cover":"https://assets.ppy.sh/beatmaps/1417543/covers/list.jpg?1622208694","id":1417543,"artist":"nonoc","title":"Memento (TV Size)","ranked_date":"2021-04-30T01:45:23+00:00"},{"count":0.6,"cover":"https://assets.ppy.sh/beatmaps/1483009/covers/list.jpg?1643130075","id":1483009,"artist":"Morimori Atsushi vs. uma","title":"Noel (long ver.)","ranked_date":null},{"count":0.6,"cover":"https://assets.ppy.sh/beatmaps/1593143/covers/list.jpg?1643313658","id":1593143,"artist":"Noah","title":"Immortal saga - Again","ranked_date":null}]